MyCalculator/__init__.py
MyCalculator/main.py
My_calculator_A_S_M_D-0.0.1.dist-info/LICENCE
My_calculator_A_S_M_D-0.0.1.dist-info/METADATA
My_calculator_A_S_M_D-0.0.1.dist-info/WHEEL
My_calculator_A_S_M_D-0.0.1.dist-info/top_level.txt
My_calculator_A_S_M_D-0.0.1.dist-info/RECORD
