Metadata-Version: 2.1
Name: My-calculator-A-S-M-D
Version: 0.0.1
Summary: simple calculator
Author: Benanberg Ayoub
Author-email: Ayoub4Benanberg@gmail.com
Classifier: Programming Language :: Python :: 3
Classifier: License :: OSI Approved :: MIT License
Classifier: Operating System :: OS Independent
License-File: LICENCE
